{
  "type": "File",
  "start": 0,
  "end": 433,
  "loc": {
    "start": {
      "line": 1,
      "column": 0
    },
    "end": {
      "line": 18,
      "column": 0
    }
  },
  "program": {
    "type": "Program",
    "start": 0,
    "end": 433,
    "loc": {
      "start": {
        "line": 1,
        "column": 0
      },
      "end": {
        "line": 18,
        "column": 0
      }
    },
    "sourceType": "module",
    "body": [
      {
        "type": "ImportDeclaration",
        "start": 21,
        "end": 49,
        "loc": {
          "start": {
            "line": 2,
            "column": 0
          },
          "end": {
            "line": 2,
            "column": 28
          }
        },
        "specifiers": [
          {
            "type": "ImportSpecifier",
            "start": 30,
            "end": 33,
            "loc": {
              "start": {
                "line": 2,
                "column": 9
              },
              "end": {
                "line": 2,
                "column": 12
              }
            },
            "imported": {
              "type": "Identifier",
              "start": 30,
              "end": 33,
              "loc": {
                "start": {
                  "line": 2,
                  "column": 9
                },
                "end": {
                  "line": 2,
                  "column": 12
                },
                "identifierName": "Api"
              },
              "name": "Api",
              "leadingComments": null
            },
            "local": {
              "type": "Identifier",
              "start": 30,
              "end": 33,
              "loc": {
                "start": {
                  "line": 2,
                  "column": 9
                },
                "end": {
                  "line": 2,
                  "column": 12
                },
                "identifierName": "Api"
              },
              "name": "Api"
            },
            "leadingComments": null
          }
        ],
        "source": {
          "type": "StringLiteral",
          "start": 41,
          "end": 48,
          "loc": {
            "start": {
              "line": 2,
              "column": 20
            },
            "end": {
              "line": 2,
              "column": 27
            }
          },
          "extra": {
            "rawValue": "./api",
            "raw": "'./api'"
          },
          "value": "./api"
        },
        "leadingComments": [
          {
            "type": "CommentBlock",
            "value": " Importing APIs ",
            "start": 0,
            "end": 20,
            "loc": {
              "start": {
                "line": 1,
                "column": 0
              },
              "end": {
                "line": 1,
                "column": 20
              }
            }
          }
        ]
      },
      {
        "type": "ImportDeclaration",
        "start": 50,
        "end": 86,
        "loc": {
          "start": {
            "line": 3,
            "column": 0
          },
          "end": {
            "line": 3,
            "column": 36
          }
        },
        "specifiers": [
          {
            "type": "ImportSpecifier",
            "start": 59,
            "end": 66,
            "loc": {
              "start": {
                "line": 3,
                "column": 9
              },
              "end": {
                "line": 3,
                "column": 16
              }
            },
            "imported": {
              "type": "Identifier",
              "start": 59,
              "end": 66,
              "loc": {
                "start": {
                  "line": 3,
                  "column": 9
                },
                "end": {
                  "line": 3,
                  "column": 16
                },
                "identifierName": "Checkin"
              },
              "name": "Checkin"
            },
            "local": {
              "type": "Identifier",
              "start": 59,
              "end": 66,
              "loc": {
                "start": {
                  "line": 3,
                  "column": 9
                },
                "end": {
                  "line": 3,
                  "column": 16
                },
                "identifierName": "Checkin"
              },
              "name": "Checkin"
            }
          }
        ],
        "source": {
          "type": "StringLiteral",
          "start": 74,
          "end": 85,
          "loc": {
            "start": {
              "line": 3,
              "column": 24
            },
            "end": {
              "line": 3,
              "column": 35
            }
          },
          "extra": {
            "rawValue": "./checkin",
            "raw": "'./checkin'"
          },
          "value": "./checkin"
        }
      },
      {
        "type": "ImportDeclaration",
        "start": 87,
        "end": 121,
        "loc": {
          "start": {
            "line": 4,
            "column": 0
          },
          "end": {
            "line": 4,
            "column": 34
          }
        },
        "specifiers": [
          {
            "type": "ImportSpecifier",
            "start": 96,
            "end": 102,
            "loc": {
              "start": {
                "line": 4,
                "column": 9
              },
              "end": {
                "line": 4,
                "column": 15
              }
            },
            "imported": {
              "type": "Identifier",
              "start": 96,
              "end": 102,
              "loc": {
                "start": {
                  "line": 4,
                  "column": 9
                },
                "end": {
                  "line": 4,
                  "column": 15
                },
                "identifierName": "Coupon"
              },
              "name": "Coupon"
            },
            "local": {
              "type": "Identifier",
              "start": 96,
              "end": 102,
              "loc": {
                "start": {
                  "line": 4,
                  "column": 9
                },
                "end": {
                  "line": 4,
                  "column": 15
                },
                "identifierName": "Coupon"
              },
              "name": "Coupon"
            }
          }
        ],
        "source": {
          "type": "StringLiteral",
          "start": 110,
          "end": 120,
          "loc": {
            "start": {
              "line": 4,
              "column": 23
            },
            "end": {
              "line": 4,
              "column": 33
            }
          },
          "extra": {
            "rawValue": "./coupon",
            "raw": "'./coupon'"
          },
          "value": "./coupon"
        }
      },
      {
        "type": "ImportDeclaration",
        "start": 122,
        "end": 154,
        "loc": {
          "start": {
            "line": 5,
            "column": 0
          },
          "end": {
            "line": 5,
            "column": 32
          }
        },
        "specifiers": [
          {
            "type": "ImportSpecifier",
            "start": 131,
            "end": 136,
            "loc": {
              "start": {
                "line": 5,
                "column": 9
              },
              "end": {
                "line": 5,
                "column": 14
              }
            },
            "imported": {
              "type": "Identifier",
              "start": 131,
              "end": 136,
              "loc": {
                "start": {
                  "line": 5,
                  "column": 9
                },
                "end": {
                  "line": 5,
                  "column": 14
                },
                "identifierName": "Event"
              },
              "name": "Event"
            },
            "local": {
              "type": "Identifier",
              "start": 131,
              "end": 136,
              "loc": {
                "start": {
                  "line": 5,
                  "column": 9
                },
                "end": {
                  "line": 5,
                  "column": 14
                },
                "identifierName": "Event"
              },
              "name": "Event"
            }
          }
        ],
        "source": {
          "type": "StringLiteral",
          "start": 144,
          "end": 153,
          "loc": {
            "start": {
              "line": 5,
              "column": 22
            },
            "end": {
              "line": 5,
              "column": 31
            }
          },
          "extra": {
            "rawValue": "./event",
            "raw": "'./event'"
          },
          "value": "./event"
        }
      },
      {
        "type": "ImportDeclaration",
        "start": 155,
        "end": 200,
        "loc": {
          "start": {
            "line": 6,
            "column": 0
          },
          "end": {
            "line": 6,
            "column": 45
          }
        },
        "specifiers": [
          {
            "type": "ImportSpecifier",
            "start": 164,
            "end": 175,
            "loc": {
              "start": {
                "line": 6,
                "column": 9
              },
              "end": {
                "line": 6,
                "column": 20
              }
            },
            "imported": {
              "type": "Identifier",
              "start": 164,
              "end": 175,
              "loc": {
                "start": {
                  "line": 6,
                  "column": 9
                },
                "end": {
                  "line": 6,
                  "column": 20
                },
                "identifierName": "EventSearch"
              },
              "name": "EventSearch"
            },
            "local": {
              "type": "Identifier",
              "start": 164,
              "end": 175,
              "loc": {
                "start": {
                  "line": 6,
                  "column": 9
                },
                "end": {
                  "line": 6,
                  "column": 20
                },
                "identifierName": "EventSearch"
              },
              "name": "EventSearch"
            }
          }
        ],
        "source": {
          "type": "StringLiteral",
          "start": 183,
          "end": 199,
          "loc": {
            "start": {
              "line": 6,
              "column": 28
            },
            "end": {
              "line": 6,
              "column": 44
            }
          },
          "extra": {
            "rawValue": "./search.event",
            "raw": "'./search.event'"
          },
          "value": "./search.event"
        }
      },
      {
        "type": "ImportDeclaration",
        "start": 201,
        "end": 235,
        "loc": {
          "start": {
            "line": 7,
            "column": 0
          },
          "end": {
            "line": 7,
            "column": 34
          }
        },
        "specifiers": [
          {
            "type": "ImportSpecifier",
            "start": 210,
            "end": 216,
            "loc": {
              "start": {
                "line": 7,
                "column": 9
              },
              "end": {
                "line": 7,
                "column": 15
              }
            },
            "imported": {
              "type": "Identifier",
              "start": 210,
              "end": 216,
              "loc": {
                "start": {
                  "line": 7,
                  "column": 9
                },
                "end": {
                  "line": 7,
                  "column": 15
                },
                "identifierName": "Ticket"
              },
              "name": "Ticket"
            },
            "local": {
              "type": "Identifier",
              "start": 210,
              "end": 216,
              "loc": {
                "start": {
                  "line": 7,
                  "column": 9
                },
                "end": {
                  "line": 7,
                  "column": 15
                },
                "identifierName": "Ticket"
              },
              "name": "Ticket"
            }
          }
        ],
        "source": {
          "type": "StringLiteral",
          "start": 224,
          "end": 234,
          "loc": {
            "start": {
              "line": 7,
              "column": 23
            },
            "end": {
              "line": 7,
              "column": 33
            }
          },
          "extra": {
            "rawValue": "./ticket",
            "raw": "'./ticket'"
          },
          "value": "./ticket"
        },
        "trailingComments": [
          {
            "type": "CommentBlock",
            "value": " Exporting APIs ",
            "start": 237,
            "end": 257,
            "loc": {
              "start": {
                "line": 9,
                "column": 0
              },
              "end": {
                "line": 9,
                "column": 20
              }
            }
          }
        ]
      },
      {
        "type": "ExportNamedDeclaration",
        "start": 258,
        "end": 432,
        "loc": {
          "start": {
            "line": 10,
            "column": 0
          },
          "end": {
            "line": 17,
            "column": 2
          }
        },
        "specifiers": [],
        "source": null,
        "declaration": {
          "type": "VariableDeclaration",
          "start": 265,
          "end": 432,
          "loc": {
            "start": {
              "line": 10,
              "column": 7
            },
            "end": {
              "line": 17,
              "column": 2
            }
          },
          "declarations": [
            {
              "type": "VariableDeclarator",
              "start": 269,
              "end": 431,
              "loc": {
                "start": {
                  "line": 10,
                  "column": 11
                },
                "end": {
                  "line": 17,
                  "column": 1
                }
              },
              "id": {
                "type": "Identifier",
                "start": 269,
                "end": 273,
                "loc": {
                  "start": {
                    "line": 10,
                    "column": 11
                  },
                  "end": {
                    "line": 10,
                    "column": 15
                  },
                  "identifierName": "apis"
                },
                "name": "apis",
                "leadingComments": null
              },
              "init": {
                "type": "ObjectExpression",
                "start": 276,
                "end": 431,
                "loc": {
                  "start": {
                    "line": 10,
                    "column": 18
                  },
                  "end": {
                    "line": 17,
                    "column": 1
                  }
                },
                "properties": [
                  {
                    "type": "ObjectProperty",
                    "start": 282,
                    "end": 298,
                    "loc": {
                      "start": {
                        "line": 11,
                        "column": 4
                      },
                      "end": {
                        "line": 11,
                        "column": 20
                      }
                    },
                    "method": false,
                    "shorthand": false,
                    "computed": false,
                    "key": {
                      "type": "Identifier",
                      "start": 282,
                      "end": 285,
                      "loc": {
                        "start": {
                          "line": 11,
                          "column": 4
                        },
                        "end": {
                          "line": 11,
                          "column": 7
                        },
                        "identifierName": "api"
                      },
                      "name": "api"
                    },
                    "value": {
                      "type": "Identifier",
                      "start": 295,
                      "end": 298,
                      "loc": {
                        "start": {
                          "line": 11,
                          "column": 17
                        },
                        "end": {
                          "line": 11,
                          "column": 20
                        },
                        "identifierName": "Api"
                      },
                      "name": "Api"
                    }
                  },
                  {
                    "type": "ObjectProperty",
                    "start": 304,
                    "end": 324,
                    "loc": {
                      "start": {
                        "line": 12,
                        "column": 4
                      },
                      "end": {
                        "line": 12,
                        "column": 24
                      }
                    },
                    "method": false,
                    "shorthand": false,
                    "computed": false,
                    "key": {
                      "type": "Identifier",
                      "start": 304,
                      "end": 311,
                      "loc": {
                        "start": {
                          "line": 12,
                          "column": 4
                        },
                        "end": {
                          "line": 12,
                          "column": 11
                        },
                        "identifierName": "checkin"
                      },
                      "name": "checkin"
                    },
                    "value": {
                      "type": "Identifier",
                      "start": 317,
                      "end": 324,
                      "loc": {
                        "start": {
                          "line": 12,
                          "column": 17
                        },
                        "end": {
                          "line": 12,
                          "column": 24
                        },
                        "identifierName": "Checkin"
                      },
                      "name": "Checkin"
                    }
                  },
                  {
                    "type": "ObjectProperty",
                    "start": 330,
                    "end": 349,
                    "loc": {
                      "start": {
                        "line": 13,
                        "column": 4
                      },
                      "end": {
                        "line": 13,
                        "column": 23
                      }
                    },
                    "method": false,
                    "shorthand": false,
                    "computed": false,
                    "key": {
                      "type": "Identifier",
                      "start": 330,
                      "end": 336,
                      "loc": {
                        "start": {
                          "line": 13,
                          "column": 4
                        },
                        "end": {
                          "line": 13,
                          "column": 10
                        },
                        "identifierName": "coupon"
                      },
                      "name": "coupon"
                    },
                    "value": {
                      "type": "Identifier",
                      "start": 343,
                      "end": 349,
                      "loc": {
                        "start": {
                          "line": 13,
                          "column": 17
                        },
                        "end": {
                          "line": 13,
                          "column": 23
                        },
                        "identifierName": "Coupon"
                      },
                      "name": "Coupon"
                    }
                  },
                  {
                    "type": "ObjectProperty",
                    "start": 355,
                    "end": 373,
                    "loc": {
                      "start": {
                        "line": 14,
                        "column": 4
                      },
                      "end": {
                        "line": 14,
                        "column": 22
                      }
                    },
                    "method": false,
                    "shorthand": false,
                    "computed": false,
                    "key": {
                      "type": "Identifier",
                      "start": 355,
                      "end": 360,
                      "loc": {
                        "start": {
                          "line": 14,
                          "column": 4
                        },
                        "end": {
                          "line": 14,
                          "column": 9
                        },
                        "identifierName": "event"
                      },
                      "name": "event"
                    },
                    "value": {
                      "type": "Identifier",
                      "start": 368,
                      "end": 373,
                      "loc": {
                        "start": {
                          "line": 14,
                          "column": 17
                        },
                        "end": {
                          "line": 14,
                          "column": 22
                        },
                        "identifierName": "Event"
                      },
                      "name": "Event"
                    }
                  },
                  {
                    "type": "ObjectProperty",
                    "start": 379,
                    "end": 403,
                    "loc": {
                      "start": {
                        "line": 15,
                        "column": 4
                      },
                      "end": {
                        "line": 15,
                        "column": 28
                      }
                    },
                    "method": false,
                    "shorthand": false,
                    "computed": false,
                    "key": {
                      "type": "Identifier",
                      "start": 379,
                      "end": 390,
                      "loc": {
                        "start": {
                          "line": 15,
                          "column": 4
                        },
                        "end": {
                          "line": 15,
                          "column": 15
                        },
                        "identifierName": "eventSearch"
                      },
                      "name": "eventSearch"
                    },
                    "value": {
                      "type": "Identifier",
                      "start": 392,
                      "end": 403,
                      "loc": {
                        "start": {
                          "line": 15,
                          "column": 17
                        },
                        "end": {
                          "line": 15,
                          "column": 28
                        },
                        "identifierName": "EventSearch"
                      },
                      "name": "EventSearch"
                    }
                  },
                  {
                    "type": "ObjectProperty",
                    "start": 409,
                    "end": 428,
                    "loc": {
                      "start": {
                        "line": 16,
                        "column": 4
                      },
                      "end": {
                        "line": 16,
                        "column": 23
                      }
                    },
                    "method": false,
                    "shorthand": false,
                    "computed": false,
                    "key": {
                      "type": "Identifier",
                      "start": 409,
                      "end": 415,
                      "loc": {
                        "start": {
                          "line": 16,
                          "column": 4
                        },
                        "end": {
                          "line": 16,
                          "column": 10
                        },
                        "identifierName": "ticket"
                      },
                      "name": "ticket"
                    },
                    "value": {
                      "type": "Identifier",
                      "start": 422,
                      "end": 428,
                      "loc": {
                        "start": {
                          "line": 16,
                          "column": 17
                        },
                        "end": {
                          "line": 16,
                          "column": 23
                        },
                        "identifierName": "Ticket"
                      },
                      "name": "Ticket"
                    }
                  }
                ]
              },
              "leadingComments": null
            }
          ],
          "kind": "var",
          "leadingComments": [
            {
              "type": "CommentBlock",
              "value": " Exporting APIs ",
              "start": 237,
              "end": 257,
              "loc": {
                "start": {
                  "line": 9,
                  "column": 0
                },
                "end": {
                  "line": 9,
                  "column": 20
                }
              }
            }
          ],
          "trailingComments": []
        },
        "leadingComments": [
          {
            "type": "CommentBlock",
            "value": " Exporting APIs ",
            "start": 237,
            "end": 257,
            "loc": {
              "start": {
                "line": 9,
                "column": 0
              },
              "end": {
                "line": 9,
                "column": 20
              }
            }
          }
        ]
      }
    ],
    "directives": []
  },
  "comments": [
    {
      "type": "CommentBlock",
      "value": " Importing APIs ",
      "start": 0,
      "end": 20,
      "loc": {
        "start": {
          "line": 1,
          "column": 0
        },
        "end": {
          "line": 1,
          "column": 20
        }
      }
    },
    {
      "type": "CommentBlock",
      "value": " Exporting APIs ",
      "start": 237,
      "end": 257,
      "loc": {
        "start": {
          "line": 9,
          "column": 0
        },
        "end": {
          "line": 9,
          "column": 20
        }
      }
    }
  ],
  "tokens": [
    {
      "type": "CommentBlock",
      "value": " Importing APIs ",
      "start": 0,
      "end": 20,
      "loc": {
        "start": {
          "line": 1,
          "column": 0
        },
        "end": {
          "line": 1,
          "column": 20
        }
      }
    },
    {
      "type": {
        "label": "import",
        "keyword": "import",
        "beforeExpr": false,
        "startsExpr": false,
        "rightAssociative": false,
        "isLoop": false,
        "isAssign": false,
        "prefix": false,
        "postfix": false,
        "binop": null,
        "updateContext": null
      },
      "value": "import",
      "start": 21,
      "end": 27,
      "loc": {
        "start": {
          "line": 2,
          "column": 0
        },
        "end": {
          "line": 2,
          "column": 6
        }
      }
    },
    {
      "type": {
        "label": "{",
        "beforeExpr": true,
        "startsExpr": true,
        "rightAssociative": false,
        "isLoop": false,
        "isAssign": false,
        "prefix": false,
        "postfix": false,
        "binop": null
      },
      "start": 28,
      "end": 29,
      "loc": {
        "start": {
          "line": 2,
          "column": 7
        },
        "end": {
          "line": 2,
          "column": 8
        }
      }
    },
    {
      "type": {
        "label": "name",
        "beforeExpr": false,
        "startsExpr": true,
        "rightAssociative": false,
        "isLoop": false,
        "isAssign": false,
        "prefix": false,
        "postfix": false,
        "binop": null
      },
      "value": "Api",
      "start": 30,
      "end": 33,
      "loc": {
        "start": {
          "line": 2,
          "column": 9
        },
        "end": {
          "line": 2,
          "column": 12
        }
      }
    },
    {
      "type": {
        "label": "}",
        "beforeExpr": false,
        "startsExpr": false,
        "rightAssociative": false,
        "isLoop": false,
        "isAssign": false,
        "prefix": false,
        "postfix": false,
        "binop": null
      },
      "start": 34,
      "end": 35,
      "loc": {
        "start": {
          "line": 2,
          "column": 13
        },
        "end": {
          "line": 2,
          "column": 14
        }
      }
    },
    {
      "type": {
        "label": "name",
        "beforeExpr": false,
        "startsExpr": true,
        "rightAssociative": false,
        "isLoop": false,
        "isAssign": false,
        "prefix": false,
        "postfix": false,
        "binop": null
      },
      "value": "from",
      "start": 36,
      "end": 40,
      "loc": {
        "start": {
          "line": 2,
          "column": 15
        },
        "end": {
          "line": 2,
          "column": 19
        }
      }
    },
    {
      "type": {
        "label": "string",
        "beforeExpr": false,
        "startsExpr": true,
        "rightAssociative": false,
        "isLoop": false,
        "isAssign": false,
        "prefix": false,
        "postfix": false,
        "binop": null,
        "updateContext": null
      },
      "value": "./api",
      "start": 41,
      "end": 48,
      "loc": {
        "start": {
          "line": 2,
          "column": 20
        },
        "end": {
          "line": 2,
          "column": 27
        }
      }
    },
    {
      "type": {
        "label": ";",
        "beforeExpr": true,
        "startsExpr": false,
        "rightAssociative": false,
        "isLoop": false,
        "isAssign": false,
        "prefix": false,
        "postfix": false,
        "binop": null,
        "updateContext": null
      },
      "start": 48,
      "end": 49,
      "loc": {
        "start": {
          "line": 2,
          "column": 27
        },
        "end": {
          "line": 2,
          "column": 28
        }
      }
    },
    {
      "type": {
        "label": "import",
        "keyword": "import",
        "beforeExpr": false,
        "startsExpr": false,
        "rightAssociative": false,
        "isLoop": false,
        "isAssign": false,
        "prefix": false,
        "postfix": false,
        "binop": null,
        "updateContext": null
      },
      "value": "import",
      "start": 50,
      "end": 56,
      "loc": {
        "start": {
          "line": 3,
          "column": 0
        },
        "end": {
          "line": 3,
          "column": 6
        }
      }
    },
    {
      "type": {
        "label": "{",
        "beforeExpr": true,
        "startsExpr": true,
        "rightAssociative": false,
        "isLoop": false,
        "isAssign": false,
        "prefix": false,
        "postfix": false,
        "binop": null
      },
      "start": 57,
      "end": 58,
      "loc": {
        "start": {
          "line": 3,
          "column": 7
        },
        "end": {
          "line": 3,
          "column": 8
        }
      }
    },
    {
      "type": {
        "label": "name",
        "beforeExpr": false,
        "startsExpr": true,
        "rightAssociative": false,
        "isLoop": false,
        "isAssign": false,
        "prefix": false,
        "postfix": false,
        "binop": null
      },
      "value": "Checkin",
      "start": 59,
      "end": 66,
      "loc": {
        "start": {
          "line": 3,
          "column": 9
        },
        "end": {
          "line": 3,
          "column": 16
        }
      }
    },
    {
      "type": {
        "label": "}",
        "beforeExpr": false,
        "startsExpr": false,
        "rightAssociative": false,
        "isLoop": false,
        "isAssign": false,
        "prefix": false,
        "postfix": false,
        "binop": null
      },
      "start": 67,
      "end": 68,
      "loc": {
        "start": {
          "line": 3,
          "column": 17
        },
        "end": {
          "line": 3,
          "column": 18
        }
      }
    },
    {
      "type": {
        "label": "name",
        "beforeExpr": false,
        "startsExpr": true,
        "rightAssociative": false,
        "isLoop": false,
        "isAssign": false,
        "prefix": false,
        "postfix": false,
        "binop": null
      },
      "value": "from",
      "start": 69,
      "end": 73,
      "loc": {
        "start": {
          "line": 3,
          "column": 19
        },
        "end": {
          "line": 3,
          "column": 23
        }
      }
    },
    {
      "type": {
        "label": "string",
        "beforeExpr": false,
        "startsExpr": true,
        "rightAssociative": false,
        "isLoop": false,
        "isAssign": false,
        "prefix": false,
        "postfix": false,
        "binop": null,
        "updateContext": null
      },
      "value": "./checkin",
      "start": 74,
      "end": 85,
      "loc": {
        "start": {
          "line": 3,
          "column": 24
        },
        "end": {
          "line": 3,
          "column": 35
        }
      }
    },
    {
      "type": {
        "label": ";",
        "beforeExpr": true,
        "startsExpr": false,
        "rightAssociative": false,
        "isLoop": false,
        "isAssign": false,
        "prefix": false,
        "postfix": false,
        "binop": null,
        "updateContext": null
      },
      "start": 85,
      "end": 86,
      "loc": {
        "start": {
          "line": 3,
          "column": 35
        },
        "end": {
          "line": 3,
          "column": 36
        }
      }
    },
    {
      "type": {
        "label": "import",
        "keyword": "import",
        "beforeExpr": false,
        "startsExpr": false,
        "rightAssociative": false,
        "isLoop": false,
        "isAssign": false,
        "prefix": false,
        "postfix": false,
        "binop": null,
        "updateContext": null
      },
      "value": "import",
      "start": 87,
      "end": 93,
      "loc": {
        "start": {
          "line": 4,
          "column": 0
        },
        "end": {
          "line": 4,
          "column": 6
        }
      }
    },
    {
      "type": {
        "label": "{",
        "beforeExpr": true,
        "startsExpr": true,
        "rightAssociative": false,
        "isLoop": false,
        "isAssign": false,
        "prefix": false,
        "postfix": false,
        "binop": null
      },
      "start": 94,
      "end": 95,
      "loc": {
        "start": {
          "line": 4,
          "column": 7
        },
        "end": {
          "line": 4,
          "column": 8
        }
      }
    },
    {
      "type": {
        "label": "name",
        "beforeExpr": false,
        "startsExpr": true,
        "rightAssociative": false,
        "isLoop": false,
        "isAssign": false,
        "prefix": false,
        "postfix": false,
        "binop": null
      },
      "value": "Coupon",
      "start": 96,
      "end": 102,
      "loc": {
        "start": {
          "line": 4,
          "column": 9
        },
        "end": {
          "line": 4,
          "column": 15
        }
      }
    },
    {
      "type": {
        "label": "}",
        "beforeExpr": false,
        "startsExpr": false,
        "rightAssociative": false,
        "isLoop": false,
        "isAssign": false,
        "prefix": false,
        "postfix": false,
        "binop": null
      },
      "start": 103,
      "end": 104,
      "loc": {
        "start": {
          "line": 4,
          "column": 16
        },
        "end": {
          "line": 4,
          "column": 17
        }
      }
    },
    {
      "type": {
        "label": "name",
        "beforeExpr": false,
        "startsExpr": true,
        "rightAssociative": false,
        "isLoop": false,
        "isAssign": false,
        "prefix": false,
        "postfix": false,
        "binop": null
      },
      "value": "from",
      "start": 105,
      "end": 109,
      "loc": {
        "start": {
          "line": 4,
          "column": 18
        },
        "end": {
          "line": 4,
          "column": 22
        }
      }
    },
    {
      "type": {
        "label": "string",
        "beforeExpr": false,
        "startsExpr": true,
        "rightAssociative": false,
        "isLoop": false,
        "isAssign": false,
        "prefix": false,
        "postfix": false,
        "binop": null,
        "updateContext": null
      },
      "value": "./coupon",
      "start": 110,
      "end": 120,
      "loc": {
        "start": {
          "line": 4,
          "column": 23
        },
        "end": {
          "line": 4,
          "column": 33
        }
      }
    },
    {
      "type": {
        "label": ";",
        "beforeExpr": true,
        "startsExpr": false,
        "rightAssociative": false,
        "isLoop": false,
        "isAssign": false,
        "prefix": false,
        "postfix": false,
        "binop": null,
        "updateContext": null
      },
      "start": 120,
      "end": 121,
      "loc": {
        "start": {
          "line": 4,
          "column": 33
        },
        "end": {
          "line": 4,
          "column": 34
        }
      }
    },
    {
      "type": {
        "label": "import",
        "keyword": "import",
        "beforeExpr": false,
        "startsExpr": false,
        "rightAssociative": false,
        "isLoop": false,
        "isAssign": false,
        "prefix": false,
        "postfix": false,
        "binop": null,
        "updateContext": null
      },
      "value": "import",
      "start": 122,
      "end": 128,
      "loc": {
        "start": {
          "line": 5,
          "column": 0
        },
        "end": {
          "line": 5,
          "column": 6
        }
      }
    },
    {
      "type": {
        "label": "{",
        "beforeExpr": true,
        "startsExpr": true,
        "rightAssociative": false,
        "isLoop": false,
        "isAssign": false,
        "prefix": false,
        "postfix": false,
        "binop": null
      },
      "start": 129,
      "end": 130,
      "loc": {
        "start": {
          "line": 5,
          "column": 7
        },
        "end": {
          "line": 5,
          "column": 8
        }
      }
    },
    {
      "type": {
        "label": "name",
        "beforeExpr": false,
        "startsExpr": true,
        "rightAssociative": false,
        "isLoop": false,
        "isAssign": false,
        "prefix": false,
        "postfix": false,
        "binop": null
      },
      "value": "Event",
      "start": 131,
      "end": 136,
      "loc": {
        "start": {
          "line": 5,
          "column": 9
        },
        "end": {
          "line": 5,
          "column": 14
        }
      }
    },
    {
      "type": {
        "label": "}",
        "beforeExpr": false,
        "startsExpr": false,
        "rightAssociative": false,
        "isLoop": false,
        "isAssign": false,
        "prefix": false,
        "postfix": false,
        "binop": null
      },
      "start": 137,
      "end": 138,
      "loc": {
        "start": {
          "line": 5,
          "column": 15
        },
        "end": {
          "line": 5,
          "column": 16
        }
      }
    },
    {
      "type": {
        "label": "name",
        "beforeExpr": false,
        "startsExpr": true,
        "rightAssociative": false,
        "isLoop": false,
        "isAssign": false,
        "prefix": false,
        "postfix": false,
        "binop": null
      },
      "value": "from",
      "start": 139,
      "end": 143,
      "loc": {
        "start": {
          "line": 5,
          "column": 17
        },
        "end": {
          "line": 5,
          "column": 21
        }
      }
    },
    {
      "type": {
        "label": "string",
        "beforeExpr": false,
        "startsExpr": true,
        "rightAssociative": false,
        "isLoop": false,
        "isAssign": false,
        "prefix": false,
        "postfix": false,
        "binop": null,
        "updateContext": null
      },
      "value": "./event",
      "start": 144,
      "end": 153,
      "loc": {
        "start": {
          "line": 5,
          "column": 22
        },
        "end": {
          "line": 5,
          "column": 31
        }
      }
    },
    {
      "type": {
        "label": ";",
        "beforeExpr": true,
        "startsExpr": false,
        "rightAssociative": false,
        "isLoop": false,
        "isAssign": false,
        "prefix": false,
        "postfix": false,
        "binop": null,
        "updateContext": null
      },
      "start": 153,
      "end": 154,
      "loc": {
        "start": {
          "line": 5,
          "column": 31
        },
        "end": {
          "line": 5,
          "column": 32
        }
      }
    },
    {
      "type": {
        "label": "import",
        "keyword": "import",
        "beforeExpr": false,
        "startsExpr": false,
        "rightAssociative": false,
        "isLoop": false,
        "isAssign": false,
        "prefix": false,
        "postfix": false,
        "binop": null,
        "updateContext": null
      },
      "value": "import",
      "start": 155,
      "end": 161,
      "loc": {
        "start": {
          "line": 6,
          "column": 0
        },
        "end": {
          "line": 6,
          "column": 6
        }
      }
    },
    {
      "type": {
        "label": "{",
        "beforeExpr": true,
        "startsExpr": true,
        "rightAssociative": false,
        "isLoop": false,
        "isAssign": false,
        "prefix": false,
        "postfix": false,
        "binop": null
      },
      "start": 162,
      "end": 163,
      "loc": {
        "start": {
          "line": 6,
          "column": 7
        },
        "end": {
          "line": 6,
          "column": 8
        }
      }
    },
    {
      "type": {
        "label": "name",
        "beforeExpr": false,
        "startsExpr": true,
        "rightAssociative": false,
        "isLoop": false,
        "isAssign": false,
        "prefix": false,
        "postfix": false,
        "binop": null
      },
      "value": "EventSearch",
      "start": 164,
      "end": 175,
      "loc": {
        "start": {
          "line": 6,
          "column": 9
        },
        "end": {
          "line": 6,
          "column": 20
        }
      }
    },
    {
      "type": {
        "label": "}",
        "beforeExpr": false,
        "startsExpr": false,
        "rightAssociative": false,
        "isLoop": false,
        "isAssign": false,
        "prefix": false,
        "postfix": false,
        "binop": null
      },
      "start": 176,
      "end": 177,
      "loc": {
        "start": {
          "line": 6,
          "column": 21
        },
        "end": {
          "line": 6,
          "column": 22
        }
      }
    },
    {
      "type": {
        "label": "name",
        "beforeExpr": false,
        "startsExpr": true,
        "rightAssociative": false,
        "isLoop": false,
        "isAssign": false,
        "prefix": false,
        "postfix": false,
        "binop": null
      },
      "value": "from",
      "start": 178,
      "end": 182,
      "loc": {
        "start": {
          "line": 6,
          "column": 23
        },
        "end": {
          "line": 6,
          "column": 27
        }
      }
    },
    {
      "type": {
        "label": "string",
        "beforeExpr": false,
        "startsExpr": true,
        "rightAssociative": false,
        "isLoop": false,
        "isAssign": false,
        "prefix": false,
        "postfix": false,
        "binop": null,
        "updateContext": null
      },
      "value": "./search.event",
      "start": 183,
      "end": 199,
      "loc": {
        "start": {
          "line": 6,
          "column": 28
        },
        "end": {
          "line": 6,
          "column": 44
        }
      }
    },
    {
      "type": {
        "label": ";",
        "beforeExpr": true,
        "startsExpr": false,
        "rightAssociative": false,
        "isLoop": false,
        "isAssign": false,
        "prefix": false,
        "postfix": false,
        "binop": null,
        "updateContext": null
      },
      "start": 199,
      "end": 200,
      "loc": {
        "start": {
          "line": 6,
          "column": 44
        },
        "end": {
          "line": 6,
          "column": 45
        }
      }
    },
    {
      "type": {
        "label": "import",
        "keyword": "import",
        "beforeExpr": false,
        "startsExpr": false,
        "rightAssociative": false,
        "isLoop": false,
        "isAssign": false,
        "prefix": false,
        "postfix": false,
        "binop": null,
        "updateContext": null
      },
      "value": "import",
      "start": 201,
      "end": 207,
      "loc": {
        "start": {
          "line": 7,
          "column": 0
        },
        "end": {
          "line": 7,
          "column": 6
        }
      }
    },
    {
      "type": {
        "label": "{",
        "beforeExpr": true,
        "startsExpr": true,
        "rightAssociative": false,
        "isLoop": false,
        "isAssign": false,
        "prefix": false,
        "postfix": false,
        "binop": null
      },
      "start": 208,
      "end": 209,
      "loc": {
        "start": {
          "line": 7,
          "column": 7
        },
        "end": {
          "line": 7,
          "column": 8
        }
      }
    },
    {
      "type": {
        "label": "name",
        "beforeExpr": false,
        "startsExpr": true,
        "rightAssociative": false,
        "isLoop": false,
        "isAssign": false,
        "prefix": false,
        "postfix": false,
        "binop": null
      },
      "value": "Ticket",
      "start": 210,
      "end": 216,
      "loc": {
        "start": {
          "line": 7,
          "column": 9
        },
        "end": {
          "line": 7,
          "column": 15
        }
      }
    },
    {
      "type": {
        "label": "}",
        "beforeExpr": false,
        "startsExpr": false,
        "rightAssociative": false,
        "isLoop": false,
        "isAssign": false,
        "prefix": false,
        "postfix": false,
        "binop": null
      },
      "start": 217,
      "end": 218,
      "loc": {
        "start": {
          "line": 7,
          "column": 16
        },
        "end": {
          "line": 7,
          "column": 17
        }
      }
    },
    {
      "type": {
        "label": "name",
        "beforeExpr": false,
        "startsExpr": true,
        "rightAssociative": false,
        "isLoop": false,
        "isAssign": false,
        "prefix": false,
        "postfix": false,
        "binop": null
      },
      "value": "from",
      "start": 219,
      "end": 223,
      "loc": {
        "start": {
          "line": 7,
          "column": 18
        },
        "end": {
          "line": 7,
          "column": 22
        }
      }
    },
    {
      "type": {
        "label": "string",
        "beforeExpr": false,
        "startsExpr": true,
        "rightAssociative": false,
        "isLoop": false,
        "isAssign": false,
        "prefix": false,
        "postfix": false,
        "binop": null,
        "updateContext": null
      },
      "value": "./ticket",
      "start": 224,
      "end": 234,
      "loc": {
        "start": {
          "line": 7,
          "column": 23
        },
        "end": {
          "line": 7,
          "column": 33
        }
      }
    },
    {
      "type": {
        "label": ";",
        "beforeExpr": true,
        "startsExpr": false,
        "rightAssociative": false,
        "isLoop": false,
        "isAssign": false,
        "prefix": false,
        "postfix": false,
        "binop": null,
        "updateContext": null
      },
      "start": 234,
      "end": 235,
      "loc": {
        "start": {
          "line": 7,
          "column": 33
        },
        "end": {
          "line": 7,
          "column": 34
        }
      }
    },
    {
      "type": "CommentBlock",
      "value": " Exporting APIs ",
      "start": 237,
      "end": 257,
      "loc": {
        "start": {
          "line": 9,
          "column": 0
        },
        "end": {
          "line": 9,
          "column": 20
        }
      }
    },
    {
      "type": {
        "label": "export",
        "keyword": "export",
        "beforeExpr": false,
        "startsExpr": false,
        "rightAssociative": false,
        "isLoop": false,
        "isAssign": false,
        "prefix": false,
        "postfix": false,
        "binop": null,
        "updateContext": null
      },
      "value": "export",
      "start": 258,
      "end": 264,
      "loc": {
        "start": {
          "line": 10,
          "column": 0
        },
        "end": {
          "line": 10,
          "column": 6
        }
      }
    },
    {
      "type": {
        "label": "var",
        "keyword": "var",
        "beforeExpr": false,
        "startsExpr": false,
        "rightAssociative": false,
        "isLoop": false,
        "isAssign": false,
        "prefix": false,
        "postfix": false,
        "binop": null,
        "updateContext": null
      },
      "value": "var",
      "start": 265,
      "end": 268,
      "loc": {
        "start": {
          "line": 10,
          "column": 7
        },
        "end": {
          "line": 10,
          "column": 10
        }
      }
    },
    {
      "type": {
        "label": "name",
        "beforeExpr": false,
        "startsExpr": true,
        "rightAssociative": false,
        "isLoop": false,
        "isAssign": false,
        "prefix": false,
        "postfix": false,
        "binop": null
      },
      "value": "apis",
      "start": 269,
      "end": 273,
      "loc": {
        "start": {
          "line": 10,
          "column": 11
        },
        "end": {
          "line": 10,
          "column": 15
        }
      }
    },
    {
      "type": {
        "label": "=",
        "beforeExpr": true,
        "startsExpr": false,
        "rightAssociative": false,
        "isLoop": false,
        "isAssign": true,
        "prefix": false,
        "postfix": false,
        "binop": null,
        "updateContext": null
      },
      "value": "=",
      "start": 274,
      "end": 275,
      "loc": {
        "start": {
          "line": 10,
          "column": 16
        },
        "end": {
          "line": 10,
          "column": 17
        }
      }
    },
    {
      "type": {
        "label": "{",
        "beforeExpr": true,
        "startsExpr": true,
        "rightAssociative": false,
        "isLoop": false,
        "isAssign": false,
        "prefix": false,
        "postfix": false,
        "binop": null
      },
      "start": 276,
      "end": 277,
      "loc": {
        "start": {
          "line": 10,
          "column": 18
        },
        "end": {
          "line": 10,
          "column": 19
        }
      }
    },
    {
      "type": {
        "label": "name",
        "beforeExpr": false,
        "startsExpr": true,
        "rightAssociative": false,
        "isLoop": false,
        "isAssign": false,
        "prefix": false,
        "postfix": false,
        "binop": null
      },
      "value": "api",
      "start": 282,
      "end": 285,
      "loc": {
        "start": {
          "line": 11,
          "column": 4
        },
        "end": {
          "line": 11,
          "column": 7
        }
      }
    },
    {
      "type": {
        "label": ":",
        "beforeExpr": true,
        "startsExpr": false,
        "rightAssociative": false,
        "isLoop": false,
        "isAssign": false,
        "prefix": false,
        "postfix": false,
        "binop": null,
        "updateContext": null
      },
      "start": 293,
      "end": 294,
      "loc": {
        "start": {
          "line": 11,
          "column": 15
        },
        "end": {
          "line": 11,
          "column": 16
        }
      }
    },
    {
      "type": {
        "label": "name",
        "beforeExpr": false,
        "startsExpr": true,
        "rightAssociative": false,
        "isLoop": false,
        "isAssign": false,
        "prefix": false,
        "postfix": false,
        "binop": null
      },
      "value": "Api",
      "start": 295,
      "end": 298,
      "loc": {
        "start": {
          "line": 11,
          "column": 17
        },
        "end": {
          "line": 11,
          "column": 20
        }
      }
    },
    {
      "type": {
        "label": ",",
        "beforeExpr": true,
        "startsExpr": false,
        "rightAssociative": false,
        "isLoop": false,
        "isAssign": false,
        "prefix": false,
        "postfix": false,
        "binop": null,
        "updateContext": null
      },
      "start": 298,
      "end": 299,
      "loc": {
        "start": {
          "line": 11,
          "column": 20
        },
        "end": {
          "line": 11,
          "column": 21
        }
      }
    },
    {
      "type": {
        "label": "name",
        "beforeExpr": false,
        "startsExpr": true,
        "rightAssociative": false,
        "isLoop": false,
        "isAssign": false,
        "prefix": false,
        "postfix": false,
        "binop": null
      },
      "value": "checkin",
      "start": 304,
      "end": 311,
      "loc": {
        "start": {
          "line": 12,
          "column": 4
        },
        "end": {
          "line": 12,
          "column": 11
        }
      }
    },
    {
      "type": {
        "label": ":",
        "beforeExpr": true,
        "startsExpr": false,
        "rightAssociative": false,
        "isLoop": false,
        "isAssign": false,
        "prefix": false,
        "postfix": false,
        "binop": null,
        "updateContext": null
      },
      "start": 315,
      "end": 316,
      "loc": {
        "start": {
          "line": 12,
          "column": 15
        },
        "end": {
          "line": 12,
          "column": 16
        }
      }
    },
    {
      "type": {
        "label": "name",
        "beforeExpr": false,
        "startsExpr": true,
        "rightAssociative": false,
        "isLoop": false,
        "isAssign": false,
        "prefix": false,
        "postfix": false,
        "binop": null
      },
      "value": "Checkin",
      "start": 317,
      "end": 324,
      "loc": {
        "start": {
          "line": 12,
          "column": 17
        },
        "end": {
          "line": 12,
          "column": 24
        }
      }
    },
    {
      "type": {
        "label": ",",
        "beforeExpr": true,
        "startsExpr": false,
        "rightAssociative": false,
        "isLoop": false,
        "isAssign": false,
        "prefix": false,
        "postfix": false,
        "binop": null,
        "updateContext": null
      },
      "start": 324,
      "end": 325,
      "loc": {
        "start": {
          "line": 12,
          "column": 24
        },
        "end": {
          "line": 12,
          "column": 25
        }
      }
    },
    {
      "type": {
        "label": "name",
        "beforeExpr": false,
        "startsExpr": true,
        "rightAssociative": false,
        "isLoop": false,
        "isAssign": false,
        "prefix": false,
        "postfix": false,
        "binop": null
      },
      "value": "coupon",
      "start": 330,
      "end": 336,
      "loc": {
        "start": {
          "line": 13,
          "column": 4
        },
        "end": {
          "line": 13,
          "column": 10
        }
      }
    },
    {
      "type": {
        "label": ":",
        "beforeExpr": true,
        "startsExpr": false,
        "rightAssociative": false,
        "isLoop": false,
        "isAssign": false,
        "prefix": false,
        "postfix": false,
        "binop": null,
        "updateContext": null
      },
      "start": 341,
      "end": 342,
      "loc": {
        "start": {
          "line": 13,
          "column": 15
        },
        "end": {
          "line": 13,
          "column": 16
        }
      }
    },
    {
      "type": {
        "label": "name",
        "beforeExpr": false,
        "startsExpr": true,
        "rightAssociative": false,
        "isLoop": false,
        "isAssign": false,
        "prefix": false,
        "postfix": false,
        "binop": null
      },
      "value": "Coupon",
      "start": 343,
      "end": 349,
      "loc": {
        "start": {
          "line": 13,
          "column": 17
        },
        "end": {
          "line": 13,
          "column": 23
        }
      }
    },
    {
      "type": {
        "label": ",",
        "beforeExpr": true,
        "startsExpr": false,
        "rightAssociative": false,
        "isLoop": false,
        "isAssign": false,
        "prefix": false,
        "postfix": false,
        "binop": null,
        "updateContext": null
      },
      "start": 349,
      "end": 350,
      "loc": {
        "start": {
          "line": 13,
          "column": 23
        },
        "end": {
          "line": 13,
          "column": 24
        }
      }
    },
    {
      "type": {
        "label": "name",
        "beforeExpr": false,
        "startsExpr": true,
        "rightAssociative": false,
        "isLoop": false,
        "isAssign": false,
        "prefix": false,
        "postfix": false,
        "binop": null
      },
      "value": "event",
      "start": 355,
      "end": 360,
      "loc": {
        "start": {
          "line": 14,
          "column": 4
        },
        "end": {
          "line": 14,
          "column": 9
        }
      }
    },
    {
      "type": {
        "label": ":",
        "beforeExpr": true,
        "startsExpr": false,
        "rightAssociative": false,
        "isLoop": false,
        "isAssign": false,
        "prefix": false,
        "postfix": false,
        "binop": null,
        "updateContext": null
      },
      "start": 366,
      "end": 367,
      "loc": {
        "start": {
          "line": 14,
          "column": 15
        },
        "end": {
          "line": 14,
          "column": 16
        }
      }
    },
    {
      "type": {
        "label": "name",
        "beforeExpr": false,
        "startsExpr": true,
        "rightAssociative": false,
        "isLoop": false,
        "isAssign": false,
        "prefix": false,
        "postfix": false,
        "binop": null
      },
      "value": "Event",
      "start": 368,
      "end": 373,
      "loc": {
        "start": {
          "line": 14,
          "column": 17
        },
        "end": {
          "line": 14,
          "column": 22
        }
      }
    },
    {
      "type": {
        "label": ",",
        "beforeExpr": true,
        "startsExpr": false,
        "rightAssociative": false,
        "isLoop": false,
        "isAssign": false,
        "prefix": false,
        "postfix": false,
        "binop": null,
        "updateContext": null
      },
      "start": 373,
      "end": 374,
      "loc": {
        "start": {
          "line": 14,
          "column": 22
        },
        "end": {
          "line": 14,
          "column": 23
        }
      }
    },
    {
      "type": {
        "label": "name",
        "beforeExpr": false,
        "startsExpr": true,
        "rightAssociative": false,
        "isLoop": false,
        "isAssign": false,
        "prefix": false,
        "postfix": false,
        "binop": null
      },
      "value": "eventSearch",
      "start": 379,
      "end": 390,
      "loc": {
        "start": {
          "line": 15,
          "column": 4
        },
        "end": {
          "line": 15,
          "column": 15
        }
      }
    },
    {
      "type": {
        "label": ":",
        "beforeExpr": true,
        "startsExpr": false,
        "rightAssociative": false,
        "isLoop": false,
        "isAssign": false,
        "prefix": false,
        "postfix": false,
        "binop": null,
        "updateContext": null
      },
      "start": 390,
      "end": 391,
      "loc": {
        "start": {
          "line": 15,
          "column": 15
        },
        "end": {
          "line": 15,
          "column": 16
        }
      }
    },
    {
      "type": {
        "label": "name",
        "beforeExpr": false,
        "startsExpr": true,
        "rightAssociative": false,
        "isLoop": false,
        "isAssign": false,
        "prefix": false,
        "postfix": false,
        "binop": null
      },
      "value": "EventSearch",
      "start": 392,
      "end": 403,
      "loc": {
        "start": {
          "line": 15,
          "column": 17
        },
        "end": {
          "line": 15,
          "column": 28
        }
      }
    },
    {
      "type": {
        "label": ",",
        "beforeExpr": true,
        "startsExpr": false,
        "rightAssociative": false,
        "isLoop": false,
        "isAssign": false,
        "prefix": false,
        "postfix": false,
        "binop": null,
        "updateContext": null
      },
      "start": 403,
      "end": 404,
      "loc": {
        "start": {
          "line": 15,
          "column": 28
        },
        "end": {
          "line": 15,
          "column": 29
        }
      }
    },
    {
      "type": {
        "label": "name",
        "beforeExpr": false,
        "startsExpr": true,
        "rightAssociative": false,
        "isLoop": false,
        "isAssign": false,
        "prefix": false,
        "postfix": false,
        "binop": null
      },
      "value": "ticket",
      "start": 409,
      "end": 415,
      "loc": {
        "start": {
          "line": 16,
          "column": 4
        },
        "end": {
          "line": 16,
          "column": 10
        }
      }
    },
    {
      "type": {
        "label": ":",
        "beforeExpr": true,
        "startsExpr": false,
        "rightAssociative": false,
        "isLoop": false,
        "isAssign": false,
        "prefix": false,
        "postfix": false,
        "binop": null,
        "updateContext": null
      },
      "start": 420,
      "end": 421,
      "loc": {
        "start": {
          "line": 16,
          "column": 15
        },
        "end": {
          "line": 16,
          "column": 16
        }
      }
    },
    {
      "type": {
        "label": "name",
        "beforeExpr": false,
        "startsExpr": true,
        "rightAssociative": false,
        "isLoop": false,
        "isAssign": false,
        "prefix": false,
        "postfix": false,
        "binop": null
      },
      "value": "Ticket",
      "start": 422,
      "end": 428,
      "loc": {
        "start": {
          "line": 16,
          "column": 17
        },
        "end": {
          "line": 16,
          "column": 23
        }
      }
    },
    {
      "type": {
        "label": ",",
        "beforeExpr": true,
        "startsExpr": false,
        "rightAssociative": false,
        "isLoop": false,
        "isAssign": false,
        "prefix": false,
        "postfix": false,
        "binop": null,
        "updateContext": null
      },
      "start": 428,
      "end": 429,
      "loc": {
        "start": {
          "line": 16,
          "column": 23
        },
        "end": {
          "line": 16,
          "column": 24
        }
      }
    },
    {
      "type": {
        "label": "}",
        "beforeExpr": false,
        "startsExpr": false,
        "rightAssociative": false,
        "isLoop": false,
        "isAssign": false,
        "prefix": false,
        "postfix": false,
        "binop": null
      },
      "start": 430,
      "end": 431,
      "loc": {
        "start": {
          "line": 17,
          "column": 0
        },
        "end": {
          "line": 17,
          "column": 1
        }
      }
    },
    {
      "type": {
        "label": ";",
        "beforeExpr": true,
        "startsExpr": false,
        "rightAssociative": false,
        "isLoop": false,
        "isAssign": false,
        "prefix": false,
        "postfix": false,
        "binop": null,
        "updateContext": null
      },
      "start": 431,
      "end": 432,
      "loc": {
        "start": {
          "line": 17,
          "column": 1
        },
        "end": {
          "line": 17,
          "column": 2
        }
      }
    },
    {
      "type": {
        "label": "eof",
        "beforeExpr": false,
        "startsExpr": false,
        "rightAssociative": false,
        "isLoop": false,
        "isAssign": false,
        "prefix": false,
        "postfix": false,
        "binop": null,
        "updateContext": null
      },
      "start": 433,
      "end": 433,
      "loc": {
        "start": {
          "line": 18,
          "column": 0
        },
        "end": {
          "line": 18,
          "column": 0
        }
      }
    }
  ]
}